chirpstack_rest_api_client/__init__.py
chirpstack_rest_api_client/schemas/__init__.py
chirpstack_rest_api_client/schemas/applications.py
chirpstack_rest_api_client/schemas/device_profiles.py
chirpstack_rest_api_client/schemas/devices.py
chirpstack_rest_api_client/schemas/gateways.py
chirpstack_rest_api_client/schemas/params.py
chirpstack_rest_api_client/schemas/tenants.py
chirpstack_rest_api_client/services/__init__.py
chirpstack_rest_api_client/services/applications.py
chirpstack_rest_api_client/services/base.py
chirpstack_rest_api_client/services/device_profiles.py
chirpstack_rest_api_client/services/devices.py
chirpstack_rest_api_client/services/gateways.py
chirpstack_rest_api_client/services/tenants.py
chirpstack_rest_api_client-0.0.1a2.dist-info/LICENSE
chirpstack_rest_api_client-0.0.1a2.dist-info/METADATA
chirpstack_rest_api_client-0.0.1a2.dist-info/WHEEL
chirpstack_rest_api_client-0.0.1a2.dist-info/top_level.txt
chirpstack_rest_api_client-0.0.1a2.dist-info/RECORD
