Metadata-Version: 2.1
Name: chirpstack_rest_api_client
Version: 0.0.1a2
Summary: A client for interacting with the Chirpstack REST API
Author: Alexandr Korochkin
Author-email: ka1ll1cit@gmail.com
License: Apache License, Version 2.0
Project-URL: Source, https://github.com/AlKorochkin/chirpstack-rest-api-client
Project-URL: Bug Tracker, https://github.com/AlKorochkin/chirpstack-rest-api-client/issues
Classifier: Development Status :: 3 - Alpha
Classifier: License :: OSI Approved :: Apache Software License
Classifier: Operating System :: OS Independent
Classifier: Programming Language :: Python :: 3.11
Requires-Python: >=3.8
License-File: LICENSE
Requires-Dist: httpx ==0.27.2
Requires-Dist: pydantic ==2.9
